gollumpy/__init__.py
gollumpy/resources/acro.short_arm.T2T.bed
gollumpy-1.0.5.dist-info/LICENSE
gollumpy-1.0.5.dist-info/METADATA
gollumpy-1.0.5.dist-info/WHEEL
gollumpy-1.0.5.dist-info/entry_points.txt
gollumpy-1.0.5.dist-info/top_level.txt
gollumpy-1.0.5.dist-info/RECORD
